nemosis/__init__.py
nemosis/compiling to exe
nemosis/custom_errors.py
nemosis/custom_tables.py
nemosis/data_fetch_methods.py
nemosis/date_generators.py
nemosis/defaults.py
nemosis/downloader.py
nemosis/favicon.ico
nemosis/filters.py
nemosis/gui.py
nemosis/hook-pandas.py
nemosis/processing_info_maps.py
nemosis/query_wrappers.py
nemosis/rows.py
nemosis/value_parser.py
nemosis/write_file_names.py
nemosis-3.8.0.dist-info/METADATA
nemosis-3.8.0.dist-info/WHEEL
nemosis-3.8.0.dist-info/licenses/LICENSE
nemosis-3.8.0.dist-info/RECORD
