Metadata-Version: 2.3
Name: nemosis
Version: 3.8.0
Summary: A tool for accessing AEMO data.
Author-email: nick-gorman <n.gorman305@gmail.com>, prakaa <abiprakash007@gmail.com>
License-File: LICENSE
Requires-Python: >=3.8
Requires-Dist: beautifulsoup4>=4.12.3
Requires-Dist: feather-format>=0.4.1
Requires-Dist: openpyxl>=3.1.5
Requires-Dist: pandas>=2.2.3
Requires-Dist: pyarrow>=17.0.0
Requires-Dist: requests>=2.32.3
Requires-Dist: xlrd>=2.0.1
